pygremlinbox_epl_2_0/__init__.py
pygremlinbox_epl_2_0-1.4.0.dist-info/licenses/LICENCE
pygremlinbox_epl_2_0-1.4.0.dist-info/METADATA
pygremlinbox_epl_2_0-1.4.0.dist-info/WHEEL
pygremlinbox_epl_2_0-1.4.0.dist-info/top_level.txt
pygremlinbox_epl_2_0-1.4.0.dist-info/RECORD
