Metadata-Version: 2.4
Name: pygremlinbox-epl-2-0
Version: 1.4.0
Summary: Supply chain security testing package with EPL-2.0 licence
Author-email: PyGremlinBox Maintainer <simon@sigre.xyz>
License: EPL-2.0
Project-URL: Homepage, https://github.com/gocortexio/pygremlinbox
Project-URL: Repository, https://github.com/gocortexio/pygremlinbox
Keywords: security,testing,licence,supply-chain
Classifier: Development Status :: 4 - Beta
Classifier: Intended Audience :: Developers
Classifier: License :: OSI Approved :: Eclipse Public License 2.0 (EPL-2.0)
Classifier: Operating System :: OS Independent
Classifier: Programming Language :: Python :: 3
Classifier: Programming Language :: Python :: 3.11
Classifier: Topic :: Security
Classifier: Topic :: Software Development :: Testing
Requires-Python: >=3.11
License-File: LICENCE
Dynamic: license-file
